agent/__init__.py
agent/config.py
agent/main.py
agent/node_config.py
cli/__init__.py
cli/main.py
cli/marlOS.py
config/__init__.py
config/mosquitto.conf
examples/__init__.py
hardware/__init__.py
hardware/arduino/arduino.ino
hardware/esp/esp.ino
marlos-1.0.5.dist-info/licenses/LICENSE
rl_trainer/__init__.py
rl_trainer/env.py
rl_trainer/evalutate.py
rl_trainer/speculation_env.py
rl_trainer/train.py
rl_trainer/train_speculation.py
rl_trainer/models/speculation_policy.zip
scripts/__init__.py
scripts/build_and_test.bat
scripts/build_and_test.sh
scripts/install-marlos.sh
scripts/install_windows.bat
scripts/post_install.py
scripts/start-node.bat
scripts/start-node.sh
scripts/test_deployment.sh
marlos-1.0.5.dist-info/METADATA
marlos-1.0.5.dist-info/WHEEL
marlos-1.0.5.dist-info/entry_points.txt
marlos-1.0.5.dist-info/top_level.txt
marlos-1.0.5.dist-info/RECORD
