Metadata-Version: 2.4
Name: marlos
Version: 1.0.5
Summary: Autonomous Distributed Computing Operating System with Reinforcement Learning
Home-page: https://github.com/ayush-jadaun/MarlOS
Author: Team async_await
Author-email: Team async_await <ayushjadaun6@gmail.com>
Maintainer-email: Ayush Jadaun <ayushjadaun6@gmail.com>
License-Expression: MIT
Project-URL: Homepage, https://github.com/ayush-jadaun/MarlOS
Project-URL: Documentation, https://github.com/ayush-jadaun/MarlOS/blob/main/README.md
Project-URL: Repository, https://github.com/ayush-jadaun/MarlOS
Project-URL: Bug Tracker, https://github.com/ayush-jadaun/MarlOS/issues
Keywords: distributed-computing,reinforcement-learning,p2p,autonomous-systems,blockchain,economics
Classifier: Development Status :: 4 - Beta
Classifier: Intended Audience :: Developers
Classifier: Intended Audience :: Science/Research
Classifier: Topic :: System :: Distributed Computing
Classifier: Topic :: Scientific/Engineering :: Artificial Intelligence
Classifier: Programming Language :: Python :: 3
Classifier: Programming Language :: Python :: 3.11
Classifier: Programming Language :: Python :: 3.12
Classifier: Operating System :: OS Independent
Classifier: Environment :: Console
Requires-Python: >=3.11
License-File: LICENSE
Requires-Dist: click>=8.0.0
Requires-Dist: rich>=13.0.0
Requires-Dist: pyzmq>=25.0.0
Requires-Dist: torch>=2.0.0
Requires-Dist: stable-baselines3>=2.0.0
Requires-Dist: gymnasium>=0.29.0
Requires-Dist: numpy>=1.24.0
Requires-Dist: websockets>=11.0.0
Requires-Dist: aiohttp>=3.8.0
Requires-Dist: cryptography>=41.0.0
Requires-Dist: pyyaml>=6.0.0
Requires-Dist: paho-mqtt>=1.6.0
Provides-Extra: dev
Requires-Dist: pytest>=7.0.0; extra == "dev"
Requires-Dist: black>=23.0.0; extra == "dev"
Requires-Dist: flake8>=6.0.0; extra == "dev"
Requires-Dist: mypy>=1.0.0; extra == "dev"
Dynamic: author
Dynamic: home-page
Dynamic: license-file
Dynamic: requires-python
